{
  "progressBar.background": "#00ffc3",
  "foreground": "#54ffa7dd",
  "selection.background": "#225596",
  "activityBar.foreground": "#fff66d",
  "scrollbar.shadow": "#282828",
  "activityBarBadge.foreground": "#f7f7f7",
  "activityBar.border": "#000000",
  "activityBar.background": "#1b1e2b",
  "sideBar.background": "#1b1e2b",
  "sideBarSectionHeader.background": "#ffffff00",
  "sideBar.border": "#000000",
  "sideBarTitle.foreground": "#c7edff",
  "sideBar.foreground": "#b1e2ff",
  "list.inactiveSelectionForeground": "#00dbff",
  "list.inactiveSelectionBackground": "#303047",
  "list.hoverForeground": "#ffffff",
  "list.hoverBackground": "#4c4c7700",
  "list.activeSelectionBackground": "#262a49",
  "list.activeSelectionForeground": "#00fff3",
  "sideBarSectionHeader.foreground": "#b1e2ff",
  "tree.indentGuidesStroke": "#b1e2ff",
  "list.dropBackground": "#2c2e47",
  "list.focusBackground": "#21445a",
  "listFilterWidget.background": "#6d3a3a",
  "list.focusForeground": "#cfcfcf",
  "listFilterWidget.outline": "#c2c2c200",
  "listFilterWidget.noMatchesOutline": "#f0564700",
  "statusBar.foreground": "#b1e2ff",
  "statusBar.background": "#1b1e2b",
  "statusBarItem.hoverBackground": "#ffffff1f",
  "statusBar.border": "#000000",
  "statusBar.debuggingBackground": "#cc3333",
  "statusBar.debuggingBorder": "#000000",
  "statusBar.noFolderBorder": "#000000",
  "statusBarItem.remoteForeground": "#b1e2ff",
  "titleBar.activeForeground": "#b1e2ff",
  "titleBar.activeBackground": "#1b1e2b",
  "titleBar.border": "#000000",
  "titleBar.inactiveBackground": "#1b1e2b",
  "titleBar.inactiveForeground": "#b1e2ff",
  "menubar.selectionForeground": "#ffffff",
  "menu.foreground": "#8d9dbc",
  "menu.selectionBackground": "#303951",
  "menu.selectionBorder": "#00000000",
  "menu.selectionForeground": "#ffffff",
  "menu.separatorBackground": "#4f677b54",
  "menu.border": "#8a7b7b00",
  "button.background": "#2a4c82",
  "input.background": "#3c3c3c",
  "textLink.foreground": "#5591d7",
  "button.hoverBackground": "#1d9bee",
  "panel.background": "#1b1e2b",
  "panel.border": "#00000059",
  "panelTitle.activeBorder": "#fff66d",
  "panelTitle.activeForeground": "#fff66d",
  "terminal.selectionBackground": "#8eb3c440",
  "badge.background": "#ff9c9c",
  "terminal.border": "#80808000",
  "badge.foreground": "#000000",
  "terminal.foreground": "#beb6b6",
  "editorGroupHeader.tabsBackground": "#292c3e",
  "menu.background": "#292c3e",
  "menubar.selectionBackground": "#292c3e",
  "tab.border": "#25252600",
  "tab.activeForeground": "#ffffff",
  "editorGroupHeader.tabsBorder": "#ff787800",
  "tab.activeBorder": "#5affb2",
  "tab.activeBackground": "#232636",
  "tab.inactiveBackground": "#292c3e",
  "tab.hoverBorder": "#00000000",
  "editorGroupHeader.border": "#1d1d21",
  "scrollbarSlider.hoverBackground": "#49485a20",
  "scrollbarSlider.background": "#49485a20",
  "editorWidget.foreground": "#b2a8a8",
  "widget.shadow": "#0000005c",
  "pickerGroup.border": "#51517100",
  "pickerGroup.foreground": "#a7caf2",
  "editorWidget.resizeBorder": "#40ffe4",
  "editorWidget.background": "#1a1c2a",
  "debugToolBar.background": "#2b2d34",
  "debugToolBar.border": "#47474700",
  "notifications.background": "#1b1e2b",
  "notifications.foreground": "#b1e2ff",
  "notificationToast.border": "#47474700",
  "notificationCenterHeader.background": "#24283b",
  "notificationCenterHeader.foreground": "#fbfbfb",
  "notificationCenter.border": "#47474700",
  "notifications.border": "#30303100",
  "editor.background": "#292c3e",
  "editorCursor.foreground": "#b3b4b2",
  "editorCursor.background": "#090028",
  "editorWhitespace.foreground": "#fbfff829",
  "editor.selectionHighlightBorder": "#00000000",
  "editor.selectionHighlightBackground": "#ffadad26",
  "editor.findMatchBorder": "#74879f00",
  "editor.findMatchHighlightBackground": "#eaa50055",
  "editor.findRangeHighlightBorder": "#f2f2f200",
  "editor.findRangeHighlightBackground": "#35445866",
  "editor.wordHighlightStrongBorder": "#ff000000",
  "editor.hoverHighlightBackground": "#a0cfff40",
  "editor.rangeHighlightBackground": "#f96f6f0b",
  "editor.wordHighlightBorder": "#ff000000",
  "editor.wordHighlightStrongBackground": "#03679fb8",
  "editor.lineHighlightBorder": "#28282800",
  "editorIndentGuide.background": "#374464",
  "editorLink.activeForeground": "#54b2ff",
  "editorRuler.foreground": "#292c3e",
  "editorIndentGuide.activeBackground": "#4c7880",
  "editorBracketMatch.background": "#ff97281c",
  "editorBracketMatch.border": "#ff9077",
  "editorError.foreground": "#ff4620",
  "editorOverviewRuler.border": "#c0afaf00",
  "editorOverviewRuler.background": "#5e5e5e00",
  "editorError.background": "#7b444200",
  "editorInfo.foreground": "#5186b6",
  "editorWarning.foreground": "#ffe46c",
  "editorGutter.background": "#292c3e",
  "editorGutter.modifiedBackground": "#26a8cd",
  "editorGutter.addedBackground": "#55ba0f",
  "editorGutter.foldingControlForeground": "#cbc4c4",
  "editorGutter.deletedBackground": "#c41f26",
  "editorCodeLens.foreground": "#9ea19c9b",
  "editorGroup.border": "#00000070",
  "tab.activeBorderTop": "#5affb200",
  "diffEditor.insertedTextBackground": "#79943a33",
  "diffEditor.insertedTextBorder": "#864c4c",
  "diffEditor.removedTextBackground": "#ff4e4e33",
  "diffEditor.border": "#00000000",
  "diffEditor.removedTextBorder": "#8a41418b",
  "editorMarkerNavigationError.background": "#8a4d4d",
  "editorMarkerNavigationInfo.background": "#527fa7",
  "editorMarkerNavigation.background": "#323245",
  "editorSuggestWidget.border": "#45454544",
  "editorSuggestWidget.background": "#292c3e",
  "editorSuggestWidget.highlightForeground": "#15c0f5",
  "editorSuggestWidget.foreground": "#8da5b6",
  "editorSuggestWidget.selectedBackground": "#1b2336",
  "editorHoverWidget.background": "#292c3e",
  "peekView.border": "#7bb4d9",
  "peekViewEditor.background": "#1c2741",
  "peekViewEditorGutter.background": "#1c2741",
  "peekViewEditor.matchHighlightBackground": "#ee860056",
  "editor.lineHighlightBackground": "#1110173c",
  "peekViewTitleLabel.foreground": "#cbfdff",
  "peekViewResult.background": "#141c30",
  "peekViewResult.fileForeground": "#b0f0ff",
  "editor.selectionBackground": "#333551",
  "peekViewTitle.background": "#1c2741",
  "editorLineNumber.activeForeground": "#b0b1ff",
  "breadcrumb.background": "#292c3e",
  "breadcrumb.focusForeground": "#b1e2ff",
  "breadcrumb.foreground": "#8899a3",
  "activityBar.inactiveForeground": "#fdfdff66",
  "editor.foldBackground": "#2831564d",
  "editor.foreground": "#b4b4b4",
  "menubar.selectionBorder": "#e60f0f00",
  "sideBarSectionHeader.border": "#00000054",
  "focusBorder": "#00699d00"
}