{
  "editorError.background": "#B73A3400",
  "menu.background": "#f5f5f5",
  "editor.findRangeHighlightBackground": "#3a3d4166",
  "editorWarning.border": "#ffffff00",
  "editor.lineHighlightBackground": "#101e2c",
  "list.activeSelectionBackground": "#0063e1",
  "button.background": "#0063e1",
  "sideBarSectionHeader.foreground": "#444444",
  "editor.selectionHighlightBackground": "#add6ff26",
  "gitDecoration.submoduleResourceForeground": "#8db9e2",
  "terminal.ansiRed": "#cd3131",
  "tree.indentGuidesStroke": "#f5f5f500",
  "terminal.ansiCyan": "#11a8cd",
  "terminal.foreground": "#cccccc",
  "list.inactiveSelectionBackground": "#d9d9d9",
  "button.secondaryForeground": "#ffffff",
  "editorWhitespace.foreground": "#3f638b",
  "widget.shadow": "#0000005c",
  "terminal.ansiBrightWhite": "#e5e5e5",
  "sideBar.foreground": "#444444",
  "diffEditor.insertedTextBorder": "default",
  "editor.findRangeHighlightBorder": "#ffffff00",
  "sideBarSectionHeader.border": "#d9d9d900",
  "textLink.foreground": "#0063e1",
  "gitDecoration.modifiedResourceForeground": "#e2c08d",
  "peekViewEditor.background": "#001f33",
  "sideBarSectionHeader.background": "#00000000",
  "terminal.ansiBlack": "#000000",
  "button.foreground": "#ffffff",
  "sideBarTitle.foreground": "#444444",
  "gitDecoration.stageDeletedResourceForeground": "#c74e39",
  "statusBarItem.remoteBackground": "#f5f5f5",
  "editorError.foreground": "#f48771",
  "diffEditor.border": "#444444",
  "diffEditor.removedTextBorder": "default",
  "terminal.ansiMagenta": "#bc3fbc",
  "button.secondaryBackground": "#333333",
  "editor.inactiveSelectionBackground": "#3a3d41",
  "activityBar.border": "#d9d9d9",
  "statusBar.background": "#f5f5f5",
  "peekViewResult.selectionBackground": "#3399ff33",
  "sideBar.background": "#f5f5f5",
  "peekViewEditorGutter.background": "#001f33",
  "peekViewEditor.matchHighlightBorder": "#ee931e",
  "tab.inactiveForeground": "#444444",
  "peekViewResult.background": "#252526",
  "peekViewResult.lineForeground": "#bbbbbb",
  "breadcrumb.background": "#152638",
  "inputOption.activeForeground": "#ffffff",
  "listFilterWidget.background": "#d9d9d9",
  "statusBar.debuggingForeground": "#444444",
  "menubar.selectionBorder": "default",
  "editorGroupHeader.tabsBorder": "default",
  "scrollbarSlider.hoverBackground": "#646464b3",
  "editorBracketMatch.background": "#0064001a",
  "editorGroupHeader.tabsBackground": "#f5f5f5",
  "terminal.ansiYellow": "#e5e510",
  "terminal.ansiGreen": "#0dbc79",
  "peekViewResult.matchHighlightBackground": "#ea5c004d",
  "statusBar.border": "#d9d9d9",
  "statusBarItem.hoverBackground": "#ffffff1f",
  "terminal.ansiWhite": "#e5e5e5",
  "peekViewTitleLabel.foreground": "#ffffff",
  "terminal.ansiBrightGreen": "#23d18b",
  "editorInfo.background": "#4490BF00",
  "button.secondaryHoverBackground": "#444444",
  "terminal.ansiBrightBlue": "#3b8eea",
  "editorInfo.border": "#4490BF00",
  "peekView.border": "#007acc",
  "gitDecoration.untrackedResourceForeground": "#73c991",
  "list.dropBackground": "#f5f5f5",
  "list.hoverBackground": "#eeeeee",
  "tab.activeBorder": "#152638",
  "list.hoverForeground": "#444444",
  "list.activeSelectionForeground": "#ffffff",
  "editor.findMatchBackground": "#515c6a",
  "scrollbar.shadow": "#000000",
  "editorGroup.border": "#444444",
  "editor.hoverHighlightBackground": "#264f7840",
  "titleBar.inactiveBackground": "#f5f5f5",
  "editor.selectionHighlightBorder": "#3f638b",
  "menubar.selectionBackground": "#ffffff1a",
  "listFilterWidget.noMatchesOutline": "#ff0000",
  "editorGutter.addedBackground": "#587c0c",
  "editorInfo.foreground": "#75beff",
  "tab.border": "#d9d9d9",
  "editorOverviewRuler.border": "#7f7f7f4d",
  "tab.activeForeground": "#ffffff",
  "editor.wordHighlightBorder": "default",
  "statusBar.debuggingBackground": "#f5f5f5",
  "editorCodeLens.foreground": "#999999",
  "editorGutter.modifiedBackground": "#0c7d9d",
  "statusBar.noFolderBackground": "#f5f5f5",
  "editorGutter.deletedBackground": "#94151b",
  "terminal.ansiBrightBlack": "#666666",
  "editorCursor.background": "#000000",
  "sideBar.border": "#d9d9d9",
  "editorGutter.background": "#152638",
  "editor.wordHighlightBackground": "#575757b8",
  "terminalCursor.foreground": "#ffffff",
  "gitDecoration.stageModifiedResourceForeground": "#e2c08d",
  "statusBar.foreground": "#444444",
  "editor.findMatchBorder": "#74879f",
  "titleBar.border": "#d9d9d9",
  "tab.inactiveBackground": "#d9d9d900",
  "activityBarBadge.foreground": "#ffffff",
  "tab.activeBackground": "#152638",
  "peekViewTitleDescription.foreground": "#ccccccb3",
  "editorError.border": "#ffffff00",
  "menu.selectionBorder": "#00000000",
  "tab.hoverForeground": "default",
  "terminal.ansiBrightYellow": "#f5f543",
  "editorLineNumber.activeForeground": "#c6c6c6",
  "terminal.ansiBrightMagenta": "#d670d6",
  "gitDecoration.conflictingResourceForeground": "#6c6cc4",
  "merge.incomingContentBackground": "#28384B",
  "editor.wordHighlightStrongBackground": "#004972b8",
  "notificationsInfoIcon.foreground": "#75beff",
  "editor.background": "#152638",
  "peekViewTitle.background": "#1e1e1e",
  "editorWarning.foreground": "#cca700",
  "terminal.ansiBlue": "#2472c8",
  "statusBar.noFolderForeground": "#444444",
  "peekViewResult.fileForeground": "#ffffff",
  "editor.rangeHighlightBackground": "#ffffff0b",
  "editor.rangeHighlightBorder": "#ffffff00",
  "statusBar.debuggingBorder": "default",
  "scrollbarSlider.background": "#79797966",
  "diffEditor.removedTextBackground": "#ff000033",
  "editor.findMatchHighlightBorder": "#ffffff00",
  "gitDecoration.ignoredResourceForeground": "#8c8c8c",
  "diffEditor.insertedTextBackground": "#9bb95533",
  "peekViewEditor.matchHighlightBackground": "#ff8f0099",
  "statusBar.noFolderBorder": "default",
  "tab.hoverBorder": "default",
  "editorGutter.foldingControlForeground": "#c5c5c5",
  "menu.selectionForeground": "#ffffff",
  "editorOverviewRuler.background": "#25252500",
  "editorSuggestWidget.highlightForeground": "#0097fb",
  "badge.foreground": "#ffffff",
  "gitDecoration.deletedResourceForeground": "#c74e39",
  "titleBar.activeBackground": "#f5f5f5",
  "terminal.ansiBrightRed": "#f14c4c",
  "peekViewResult.selectionForeground": "#ffffff",
  "tab.activeBorderTop": "#00000000",
  "statusBarItem.remoteForeground": "#444444",
  "listFilterWidget.outline": "#00000000",
  "editorWarning.background": "#A9904000",
  "list.focusForeground": "#cccccc",
  "editor.foldBackground": "#101e2c",
  "titleBar.activeForeground": "#444444",
  "merge.incomingHeaderBackground": "#395F8F",
  "gitDecoration.addedResourceForeground": "#81b88b",
  "editor.wordHighlightStrongBorder": "default",
  "scrollbarSlider.activeBackground": "#bfbfbf66",
  "editorBracketMatch.border": "#ffffff",
  "editorGroupHeader.border": "default",
  "editorLineNumber.foreground": "#858585",
  "list.inactiveSelectionForeground": "#444444",
  "terminal.ansiBrightCyan": "#29b8db",
  "button.hoverBackground": "#0070ff",
  "editor.lineHighlightBorder": "#28282800",
  "tab.hoverBackground": "default",
  "menu.foreground": "#444444",
  "editor.foreground": "#ffffff",
  "editorHoverWidget.background": "#101e2c",
  "editorHoverWidget.border": "#ffffff",
  "editorHoverWidget.foreground": "#ffffff",
  "editorSuggestWidget.background": "#101e2c",
  "editorSuggestWidget.foreground": "#ffffff",
  "editorSuggestWidget.selectedBackground": "#152638",
  "editorSuggestWidget.border": "#ffffff",
  "merge.commonContentBackground": "#101e2c",
  "merge.currentContentBackground": "#195816",
  "merge.currentHeaderBackground": "#2a9625",
  "merge.commonHeaderBackground": "#51565a",
  "editorMarkerNavigationError.background": "#fc4349",
  "editorMarkerNavigationWarning.background": "#fecb57",
  "editorMarkerNavigationInfo.background": "#73d5e9",
  "editorMarkerNavigation.background": "#101e2c",
  "editorCursor.foreground": "#ffffff",
  "editor.selectionBackground": "#3f638b",
  "editor.findMatchHighlightBackground": "#38649663",
  "editorRuler.foreground": "#243c55",
  "editorIndentGuide.background": "#243c55",
  "editorLink.activeForeground": "#73d5e9",
  "editorIndentGuide.activeBackground": "#36597d",
  "activityBar.background": "#f5f5f5",
  "activityBar.inactiveForeground": "#777777",
  "activityBar.foreground": "#555555",
  "activityBar.activeBackground": "#d9d9d9",
  "activityBarBadge.background": "#0063e1",
  "notificationsWarningIcon.foreground": "#fecb57",
  "notificationsErrorIcon.foreground": "#fc4349",
  "notifications.background": "#f5f5f5",
  "notificationToast.border": "#d9d9d9",
  "menu.selectionBackground": "#0063e1",
  "notificationCenter.border": "#d9d9d9",
  "notificationCenterHeader.background": "#d9d9d9",
  "notifications.border": "#d9d9d9",
  "menu.separatorBackground": "#d9d9d9",
  "notificationCenterHeader.foreground": "#444444",
  "notifications.foreground": "#444444",
  "menubar.selectionForeground": "#444444",
  "menu.border": "#d9d9d9",
  "titleBar.inactiveForeground": "#444444",
  "terminalCursor.background": "#0063e1",
  "badge.background": "#fc4349",
  "panel.border": "#243c55",
  "terminal.border": "#243c55",
  "panelTitle.activeBorder": "#f5f5f5",
  "panelTitle.activeForeground": "#f5f5f5",
  "terminal.selectionBackground": "#3f638b42",
  "panelTitle.inactiveForeground": "#f5f5f5",
  "breadcrumb.focusForeground": "#f5f5f5",
  "breadcrumb.foreground": "#ffffff",
  "editorWidget.background": "#f5f5f5",
  "editorWidget.foreground": "#444444",
  "pickerGroup.border": "#d9d9d9",
  "editorWidget.resizeBorder": "#d9d9d9",
  "debugToolBar.background": "#f5f5f5",
  "pickerGroup.foreground": "#0063e1",
  "debugToolBar.border": "#d9d9d9",
  "focusBorder": "#d9d9d9",
  "progressBar.background": "#40ea37",
  "foreground": "#444444",
  "selection.background": "#b3d7ff",
  "input.foreground": "#444444",
  "input.border": "#d9d9d9",
  "input.placeholderForeground": "#afadae",
  "inputOption.activeBackground": "#0063e1",
  "inputOption.activeBorder": "#d9d9d900",
  "input.background": "#ffffff",
  "list.highlightForeground": "#0063e1",
  "list.focusBackground": "#d9d9d9",
  "panel.background": "#101e2ce9"
}